{
  "country": "mw",
  "language": "ch",
  "version": "1.0.0",
  "hymns": [
    {
      "number": 1,
      "previous_version_number": null,
      "title": "Oyera, Oyera, Oyera",
      "writer": "--",
      "rating": 4.9,
      "tags": ["hymn"],
      "crossReference": [
      {
          "countryCode": "mw",
          "languageCode": "en",
          "hymnNumber": 1
        }
      ],
      "content": {
        "verses": [
          {
            "number": 1,
            "lines": [
              "Oyera, Oyera, Oyera! Mulungu wa mphamvu zonse!",
              "M'mawa tidzayimba nyimbo...;",
              "Oyera, Oyera, Oyera! Wachifundo chosatha!",
              "Mlungu mu utatu, Odalitsika!"
            ]
          },
          {
            "number": 2,
            "lines": [
              "Oyera, Oyera, Oyera! Mulungu wa mphamvu zonse!"
            ]
          }
        ],
        "chorus": null
      }
    },
    {
      "number": 2,
      "previous_version_number": null,
      "title": "Nyimbo 2",
      "writer": "",
      "rating": 4.9,
      "tags": ["nyimbo"],
      "content": {
        "verses": [
          {
            "number": 1,
            "lines": []
          }
        ],
        "chorus": null
      }
    },
    {
      "number": 3,
      "previous_version_number": null,
      "title": "Nyimbo 3",
      "writer": "",
      "rating": 0,
      "tags": ["nyimbo"],
      "content": {
        "verses": [
          {
            "number": 1,
            "lines": []
          }
        ],
        "chorus": null
      }
    },
    {
      "number": 4,
      "previous_version_number": 2,
      "title": "Lemekeza Mulungu Tate",
      "writer": "",
      "rating": 0,
      "tags": ["nyimbo"],
      "content": {
        "verses": [
          {
            "number": 1,
            "lines": [
              "INU Mulungi, tikuyamikani;",
              "Tivomereza ndinu Ambuyathu;",
              "Ponse, Atate, akugwadirani;",
              "Ndinu wamuyaya!"
            ]
          },
          {
            "number": 2,
            "lines": [
              "Inu akukuzani amithenga;",
              "nanu zam'mwamba ndi zamphamvu zake;",
              "Nanu angelo amitundu yonse;",
              "Akuimbirani."
            ]
          },
          {
            "number": 3,
            "lines": [
              "\"Mbuye Woyera! E, Woyera nokha!",
              "Mbuye Woyera! Mbuye wa makamu!",
              "Ponse ulemu wanu ndi wodzadza;",
              "Pansi ndi Kumwamba\""
            ]
          },
          {
            "number": 4,
            "lines": [
              "Inu atumwi akumveka aja,",
              "Ndi aneneri iyanjana omwe;",
              "Ndi aunyinji anakuferani;",
              "Akuyamikani"
            ]
          },
          {
            "number": 5,
            "lines": [
              "Mpingo Woyera! wa kwa anthu onse;",
              "Ukumverani, Mfumu ndi Atate;",
              "Mwana woona waulemu wonse,",
              "Mzimu, Nkhoswe yemwe."
            ]
          },
          {
            "number": 6,
            "lines": [
              "Khristu Mfumu ya ulemelero!",
              "Mwana wosatha wa Atate Ndinu!",
              "Simunanyoze mimba ya namwali;",
              "Potipulumutsa."
            ]
          },
          {
            "number": 7,
            "lines": [
              "Imfa mutagonjetsa ndi zowawa;",
              "Njira munatsekula tikalowe;",
              "Momwe mukhala Inu ndi Atate;",
              "Mu ulemelero."
            ]
          },
          {
            "number": 8,
            "lines": [
              "Kumva milandu yathu mudzabwera;",
              "Mutithandize atumiki anu;",
              "Mwatiwombola nao mwazi wanu;",
              "Mutipulumutse."
            ]
          },
          {
            "number": 9,
            "lines": [
              "M'tiwerengere M'mwamba ndi oyera;",
              "Mutidalitse ndi'fe anthu anu;",
              "Moyo wosatha mutipatse tonse;",
              "Mutilamulire."
            ]
          },
          {
            "number": 10,
            "lines": [
              "Tsiku ndi tsiku timalemekeza;",
              "Inu tikukuzani osaleka;",
              "Mbuye, m'tisunge tisachimwe lero;",
              "M'tichitire nsinsi."
            ]
          },
          {
            "number": 11,
            "lines": [
              "Mbuye chifundo chanu chitigwere;",
              "Monga tikhulupi'ra Inu nokha;",
              "Tikhulupi'ra zedi mwa 'Nu, Mbuye;",
              "Tisagome konse!"
            ]
          }
        ],
        "chorus": null
      }
    },
    {
      "number": 5,
      "previous_version_number": 3,
      "title": "ATATE wa Kumwambako",
      "writer": "",
      "rating": 0,
      "tags": ["nyimbo"],
      "content": {
        "verses": [
          {
            "number": 1,
            "lines": [
              "ATATE wa Kumwambako,",
              "Munawombola ife, ndi ", 
              "Chikondi chanu chijacho",
              "Tiyamikira Inutu."
            ]
          },
          {
            "number": 2,
            "lines": [
              "Ambuye Yesu Inutu",
              "Munabadwira anthu'fe",
              "Munatifera tonse'fe",
              "Tiyamikira Inutu"
            ]
          },
          {
            "number": 3,
            "lines": [
              "Mzimu Woyera m'mtimamo,",
              "Tiyeretsedwe ndi Inutu",
              "Munatisunga bwinoli,",
              "Tiyamikira Inutu."
            ]
          },
          {
            "number": 4,
            "lines": [
              "Atate, Mwana, Mzimunso,",
              "Ndinu atatu, Mmodzitu",
              "Ochimwa tikupemphani",
              "Mutikululukire'fe."
            ]
          }
        ],
        "chorus": null
      }
    },
    {
      "number": 6,
      "previous_version_number": 4,
      "title": "Lemekeza Mlungu `Tate",
      "writer": "",
      "rating": 0,
      "tags": ["nyimbo"],
      "content": {
        "verses": [
          {
            "number": 1,
            "lines": [
              "LEMEKEZA Mlungu `Tate,",
              "Lemekeza Mlungu Mwana;",
              "Lemekeza Mlungu Mzimu,",
              "Mlungu Mmodzi ndi Wamkulu,",
              "Lemekeza, lemekeza,",
              "Mlungu wathu yemweyo."
            ]
          },
          {
            "number": 2,
            "lines": [
              "M'lemekeze, anakonda,",
              "Natitsuka m'mtima mwathu;",
              "Anatiwombola ife",
              "Tikakhale ndi chifumu.",
              "Lemekeza, lemekeza,",
              "Yesu Mbuye Nsembeyo."
            ]
          },
          {
            "number": 3,
            "lines": [
              "Lemekeza Mfumu yathu,",
              "Mfumu ya mipingo yonse;",
              "Ipambana anthu onse",
              "Akumwamba ndi apansi",
              "Lemekeza, lemekeza,",
              "Mfumu ya mafumuyo."
            ]
          }
        ],
        "chorus": null
      }
    },
    {
      "number": 7,
      "previous_version_number": 5,
      "title": "NDI Aleluya imbirani",
      "writer": "",
      "rating": 0,
      "tags": ["nyimbo"],
      "content": {
        "verses": [
          {
            "number": 1,
            "lines": [
              "NDI Aleluya imbirani,",
              "'Tate wathu Wakumwamba",
              "Analenga zonse;",
              "Chifundo chake  chachikulu,",
              "Nzeru, mphamvu ndi ufumu.",
              "Tiyamike tonse."
            ]
          },
          {
            "number": 2,
            "lines": [
              "Ndi Aleluya imbirani",
              "Yesu Khristu Mpulumutsi",
              "Anachoka kwawo;",
              "...."
            ]
          }
        ],
        "chorus": null
      }
    },
    {
      "number": 8,
      "previous_version_number": null,
      "title": "--",
      "writer": "",
      "rating": 0,
      "tags": ["nyimbo"],
      "content": {
        "verses": [
          
        ],
        "chorus": null
      }
    },
    {
      "number": 9,
      "previous_version_number": null,
      "title": "--",
      "writer": "",
      "rating": 0,
      "tags": ["nyimbo"],
      "content": {
        "verses": [
          
        ],
        "chorus": null
      }
    },
    {
      "number": 10,
      "previous_version_number": null,
      "title": "--",
      "writer": "",
      "rating": 0,
      "tags": ["nyimbo"],
      "content": {
        "verses": [
          
        ],
        "chorus": null
      }
    },
    {
      "number": 11,
      "previous_version_number": 9,
      "title": "E, Chifundo chake",
      "writer": "",
      "rating": 0,
      "tags": ["nyimbo"],
      "content": {
        "verses": [
          {
            "number": 1,
            "lines": [
              "NDI mitima yokondwera,",
              "Mbuye wathu tiyamika."
            ]
          },
          {
            "number": 2,
            "lines": [
              "Dzina lake tibukitsa,",
              "Mlungu ndiye yekhayekha."
            ]
          },
          {
            "number": 3,
            "lines": [
              "Mphamvu yake inalenga,",
              "Dziko lonse ndi Kumwamba."
            ]
          },
          {
            "number": 4,
            "lines": [
              "Anatsogolera kale,",
              "M'chipululu anthu ake."
            ]
          },
          {
            "number": 5,
            "lines": [
              "Ndi chifundo atipenya,",
              "Ife anthu osauka."
            ]
          },
          {
            "number": 6,
            "lines": [
              "Amaweta nyama zonse,",
              "Zingasowe kanthu konse."
            ]
          },
          {
            "number": 7,
            "lines": [
              "Tiimbire Mlungu wathu",
              "Waulemu ndi Wamkulu."
            ]
          },
          {
            "number": 8,
            "lines": [
              "Tithawire kwa Mulungu",
              "Ndiko tikapeze moyo."
            ]
          }
        ],
        "chorus": {
          "lines": [
            "E, chifundo chake chonse,",
            "Ndichosatha nthawi zonse."
          ]
        }
      }
    },
    {
      "number": 12,
      "previous_version_number": null,
      "title": "Nditamatu Ambuyanga",
      "writer": "",
      "rating": 0,
      "tags": ["nyimbo", "Masalimo 146:2"],
      "content": {
        "verses": [
          {
            "number": 1,
            "lines": [
              "NDITAMATU Ambuyangayu,",
              "Moyo wanga wonse ndidzam'tamatu;",
              "Ndiponso m'dziko la Kumwambako.",
              "Masiku anga onse ndidzam'lemekeza Iye,",
              "Sindidzaleka konsekonse mmene ndiri moyotu;",
              "Pa dziko pano pena M'mwambamo."
            ]
          },
          {
            "number": 2,
            "lines": [
              "Ndiye wokondwa, E,", "munthuyo,",
              "Wokhulupilira Mlungu yekhadi;",
              "Wolenga dziko, nyanja, zonsezi.",
              "Choona chake chonse chingokhalatu chosatha,",
              "Apulumutsa onse namadyetsa anthu akewo;",
              "Wokonda ndiye Mlungu wathuyo."
            ]
          },
          {
            "number": 3,
            "lines": [
              "Mlungu kuona athiratu,",
              "Inde m'maso awo osapenyawo;",
              "Natuma akumvera mpumulo.",
              "Amathandiza inde a ulendo ofokatu,",
              "Akazi amasiye, maka ndi ana'wo onsewo;",
              "Olira otonthoza mtimadi."
            ]
          },
          {
            "number": 4,
            "lines": [
              "Nditamatu Ambuyangayu,",
              "Moyo wanga wonse ndidzam'tamatu;",
              "Ndiponso m'dziko la Kumwambako.",
              "Masiku anga onse ndidzam'lemekeza Iye,",
              "Sindidzaleka konsekonse mmene ndiri moyotu;",
              "Pa dziko pano pena M'mwambamo."
            ]
          }
        ],
        "chorus": null
      }
    },
    {
      "number": 13,
      "previous_version_number": 11,
      "title": "Mulungu alinane",
      "writer": "",
      "rating": 0,
      "tags": ["nyimbo", "Masalimo 139"],
      "content": {
        "verses": [
          {
            "number": 1,
            "lines": [
              "PAPHIRI ndi padambo, Ponsepo pali Mlungu;",
              "Pyenda ife m'njira, Mpoima pali Mlungu.",
              "Kokwra maganizo, Komweko kuli Mlungu;",
              "Kumwamba ndi pansipo, Ponsepo pali Mlungu."
            ]
          },
          {
            "number": 2, 
            "lines": [
              "Ndi maso Ambuyathu, Apenyetsetsa ife;",
              "Amadalitsa onse, Okhulupi'ra Iye.",
              "Amamva timbalame, Naveka dziko lonse;",
              "Sataya tizirombo, Asunga zina zonse."
            ]
          },
          {
            "number": 3,
            "lines": [
              "Okwawa pansi inu, Oyenda m'madzi inu;",
              "Oyesa dziko n'kwanu, A m'mlengalenga inu.",
              "Nonsenu ntchito zake, Muona tsiku n'tsiku;",
              "Saleka kusamala, Ndi kudalitsa inu."
            ]
          },
          {
            "number": 4,
            "lines": [
              "Nditama mphamvu yake, Ya Mlungu yondizinga;",
              "N'kafoka andilimbitsa, N'kadwala andichiza.",
              "Pakundisiya bwenzi, Mulungu ali paja;",
              "N'kalowa imfa ine, Alipo Mlungu wanga."
            ]
          }
        ],
        "chorus": {
          "lines": [
            "(Mulungu ali nane!)",
            "",
            "(Ali nane, ali nane",
            "ali nane, ali nane, Aa!",
            "Mulungu ali nane!)"
          ]
        }
      }
    },
    {
      "number": 14,
      "previous_version_number": 12,
      "title": "Ife tonse tiyamike Mlunguyo",
      "writer": "",
      "rating": 0,
      "tags": ["nyimbo"],
      "content": {
        "verses": [
          {
            "number": 1,
            "lines": [
              "MTIMA wanga uyamike,",
              "Mfumu ya Kumwambako,",
              "Anandiwombola ine;",
              "Nanditsuka m'mtimamo."
            ]
          },
          {
            "number": 2,
            "lines": [
              "Tiyamike Mlungu wathu,",
              "Kaamba ka chifundocho;",
              "Nthawi zonse sasinthika,",
              "Mlungi wathu yemweyo."
            ]
          },
          {
            "number": 3,
            "lines": [
              "Nthawi zonse monga 'Tate",
              "Atisamaliratu;",
              "Atisunga m'manja mwake",
              "Atipulumutsatu."
            ]
          },
          {
            "number": 4,
            "lines": [
              "Anthu a mitundu yonse,",
              "Ndiponso a Kumwamba;",
              "Yamikani Mlungu wathu",
              "Ndiye wakukomatu."
            ]
          },
          {
            "number": "last_chorus",
            "lines": [
              "Anthu onse, anthu onse,",
              "Yamikani Mlunguyo."
            ]
          }
        ],
        "chorus": {
          "lines": [
            "Ife tonse, ife tonse",
            "Tiyamike Mlunguyo,"
          ]
        }
      }
    },
    {
      "number": 15,
      "previous_version_number": 13,
      "title": "Yehova ndiye M'busa wanga",
      "writer": "",
      "rating": 0,
      "tags": ["nyimbo", "Masalimo 23"],
      "content": {
        "verses": [
          {
            "number": 1,
            "lines": [
              "YEHOVA ndiye M'busa wanga,",
              "Sin'ngasowe konse;",
              "Andigonetsa pali busa",
              "La misipu yonse."
            ]
          },
          {
            "number": 2,
            "lines": [
              "Kumadzi kuli njiratu,",
              "Andiyendetsa bwino;",
              "Nalimbikitsa moyo wanga,",
              "Ndi chifundo chake."
            ]
          },
          {
            "number": 3,
            "lines": [
              "Pabande lolunjika,",
              "Andilondolera njira;",
              "Chifukwacho cha dzina lake,",
              "Anandisungira."
            ]
          },
          {
            "number": 4,
            "lines": [
              "Chigwa choopsacho cha imfa,",
              "Ndikachilowera;",
              "Ndilibe mantha, muli ndi'ne",
              "Ndodo ndiigwira."
            ]
          },
          {
            "number": 5,
            "lines": [
              "Pamaso pa adaniwo,",
              "Mwayala gome langa;",
              "E, mutu mwaudzoza,",
              "Chisefuka chikho changa."
            ]
          },
          {
            "number": 6,
            "lines": [
              "Zabwino ndi zokoma,",
              "Zinditsata chitsatire;",
              "E, m'nyumba ya Yehova,",
              "Ndidzakhala chikalire."
            ]
          }
        ],
        "chorus": {
          "lines": [
            "(Ndiye M'busa wanga,",
            "Ndiye M'busa wanga!,",
            "Yehova ndiye M'busa wanga.",
            "Sin'ngasowe konse)"
          ]
        }
      }
    },
    {
      "number": 16,
      "previous_version_number": 14,
      "title": "Mtima wanga lemekeza",
      "writer": "",
      "rating": 0,
      "tags": ["nyimbo"],
      "content": {
        "verses": [
          {
            "number": 1,
            "lines": [
              "MTIMA wanga  lemekeza,",
              "Mlungu wako ndi chimwemwe;",
              "Nthawi zonse ndimtamanda,",
              "Ndimuyimbira nyimbo zanga.",
              "Moyo, mphamvu, nzeru zonse,",
              "Zidzamlemekeza konse."
            ]
          },
          {
            "number": 2,
            "lines": [
              "Ndi wamwayi munthu uja,",
              "Am'thandiza Mbuye wake;",
              "Akachita mantha iye,",
              "Am'chotsera nkhawa yake.",
              "Ndipo likam'gwera tsoka,",
              "Amakhulupi'ra kokha."
            ]
          },
          {
            "number": 3,
            "lines": [
              "Mbuye ndiye wachifundo,",
              "Achiritsa akudwala;",
              "Anyamula akufoka,",
              "Nawadyetsatu a njala.",
              "Wakusunga mlendo ndiye,",
              "Nathandiza amasiye."
            ]
          },
          {
            "number": 4,
            "lines": [
              "Ndiye Mbuye wa ambuye,",
              "Mphamvu yake ndi yokwana;",
              "Adzakhala chikhalire.",
              "Mfumu yathu yopambana.",
              "Aleluya! Kondwerani!",
              "Mlungu wathu yamikani."
            ]
          }
        ],
        "chorus": null
      }
    },
    {
      "number": 17,
      "previous_version_number": 15,
      "title": "Mulungu ndiye M'busa wanga",
      "writer": "",
      "rating": 0,
      "tags": ["nyimbo", "Masalimo 23"],
      "content": {
        "verses": [
          {
            "number": 1,
            "lines": [
              "MULUNGU ndiye M'busa wanga,",
              "Sindisowa konse;",
              "Amandiweta nandidyetsa,",
              "Nandipatsa zonse."
            ]
          },
          {
            "number": 2,
            "lines": [
              "M'mitsinje yamtendere mtima,",
              "Wanga aumwetsa;",
              "Mapazi omwe m'njira,",
              "Yolungama nayendetsa."
            ]
          },
          {
            "number": 3,
            "lines": [
              "Za mdima, infa, nkhondo ndi",
              "Zoipa sindiopa;",
              "Ndikakhumudwa ndi kutopa,",
              "Andipulumutsa."
            ]
          },
          {
            "number": 4,
            "lines": [
              "Podwala ine, povutidwa,",
              "Andisamalira;",
              "Pondisautsa 'dani anga,",
              "Nandithangatira."
            ]
          },
          {
            "number": 5,
            "lines": [
              "Chisomo ndi zokoma zake,",
              "Sizileka konse;",
              "Ndi m'nyumba ya Mulungu,",
              "Ndidzakhala nsiku zonse."
            ]
          }
        ],
        "chorus": {
          "lines": [
            "(Ndiye M'busa wanga,",
            "Ndiye M'busa wanga!,",
            "Mulungu ndiye M'busa wanga.",
            "Sindisowa konse.)"
          ]
        }
      }
    },
    {
      "number": 18,
      "title": "Pokhala inu mpotikonda ndithu",
      "previous_version_number": 84,
      "writer": "",
      "rating": 0,
      "tags": ["nyimbo", "Masalimo 84"],
      "content": {
        "verses": [
          {
            "number": 1,
            "lines": [
              "POKHALA inu mpotikonda ndithu,",
              "Yehova Wamakamu.",
              "Moyo wanga; ulakalaka Inu,",
              "Ukomokanso ndikufuna,",
              "Mabwalo a Yehova.",
              "Mtima wanga ndi thupi langa,",
              "Zifuulira kwa Mulungu wa moyo."
            ]
          },
          {
            "number": 2,
            "lines": [
              "Odala iwotu akugonera,",
              "M'nyumba mwanu Yehova;",
              "Nthawi zonse akulemekezani,",
              "Odala munthu yemwe,",
              "Mphamvu yake iri mwa Inu;",
              "Mu mtima mwake ndi moyera",
              "Mulitu makwalala a ku Zioni."
            ]
          }
        ],
        "chorus": null
      }
    },
    {
      "number": 19,
      "title": "MULUNGU akhale nao",
      "previous_version_number": 310,
      "writer": "",
      "rating": 0,
      "tags": ["nyimbo"],
      "crossReference": [],
      "content": {
        "verses": [
          {
            "number": 1,
            "lines": [
              "MULUNGU akhale nao,",
              "Ulemelero ndi dalitso,",
              "Ndiye Atate, Mwana,",
              "Mzimu Woyera, Mlungu Mmodzi."
            ]
          },
          {
            "number": 2,
            "lines": [
              "tsopano, poyamba paja,",
              "Masiku onse alinkudza;",
              "Mphamvu, ulemelero,",
              "Dalitso, chipambano."
            ]
          }
        ]
      }
    },
    {
      "number": 20,
      "title": "CHIKONDI cha Mulungu wathu",
      "previous_version_number": null,
      "writer": "",
      "rating": 0,
      "tags": ["nyimbo"],
      "crossReference": [],
      "content": {
        "verses": [
          {
            "number": 1,
            "lines": [
              "CHIKONDI cha Mulungi wathu,",
              "Kutumiza Mwana wakeyo,",
              "Kutifera ife tonse'fe,",
              "Kutipulumitsa."
            ]
          },
          {
            "number": 2,
            "lines": [
              "Mtima wanu usavutike,",
              "Khulupilirani Mulungu;",
              "Khulupilirani Inenso,",
              "Mudzapulumuka."
            ]
          }
        ],
        "chorus": {
          "lines": [
            "Kweza, kweza maso,",
            "Kwa Atate.",
            "Udzalnadilra moyo,",
            "Wosathawo."
          ]
        }
      }
    }
  ]
}